{
  "__inputs": [
    {
      "name": "DS_TIMESCALE",
      "label": "Timescale",
      "description": "",
      "type": "datasource",
      "pluginId": "postgres",
      "pluginName": "PostgreSQL"
    }
  ],
  "__elements": {},
  "__requires": [
    {
      "type": "panel",
      "id": "barchart",
      "name": "Bar chart",
      "version": ""
    },
    {
      "type": "panel",
      "id": "dashlist",
      "name": "Dashboard list",
      "version": ""
    },
    {
      "type": "panel",
      "id": "gauge",
      "name": "Gauge",
      "version": ""
    },
    {
      "type": "grafana",
      "id": "grafana",
      "name": "Grafana",
      "version": "9.5.2"
    },
    {
      "type": "panel",
      "id": "heatmap",
      "name": "Heatmap",
      "version": ""
    },
    {
      "type": "panel",
      "id": "piechart",
      "name": "Pie chart",
      "version": ""
    },
    {
      "type": "datasource",
      "id": "postgres",
      "name": "PostgreSQL",
      "version": "1.0.0"
    },
    {
      "type": "panel",
      "id": "table",
      "name": "Table",
      "version": ""
    },
    {
      "type": "panel",
      "id": "timeseries",
      "name": "Time series",
      "version": ""
    }
  ],
  "annotations": {
    "list": [
      {
        "builtIn": 1,
        "datasource": {
          "type": "grafana",
          "uid": "-- Grafana --"
        },
        "enable": true,
        "hide": true,
        "iconColor": "rgba(0, 211, 255, 1)",
        "name": "Annotations & Alerts",
        "type": "dashboard"
      }
    ]
  },
  "editable": true,
  "fiscalYearStartMonth": 0,
  "graphTooltip": 0,
  "id": null,
  "links": [],
  "liveNow": false,
  "panels": [
    {
      "datasource": {
        "type": "postgres",
        "uid": "${DS_TIMESCALE}"
      },
      "fieldConfig": {
        "defaults": {
          "color": {
            "mode": "palette-classic"
          },
          "custom": {
            "axisCenteredZero": false,
            "axisColorMode": "text",
            "axisLabel": "",
            "axisPlacement": "left",
            "fillOpacity": 80,
            "gradientMode": "none",
            "hideFrom": {
              "legend": false,
              "tooltip": false,
              "viz": false
            },
            "lineWidth": 1,
            "scaleDistribution": {
              "type": "linear"
            },
            "thresholdsStyle": {
              "mode": "off"
            }
          },
          "mappings": [],
          "thresholds": {
            "mode": "absolute",
            "steps": [
              {
                "color": "green",
                "value": null
              },
              {
                "color": "red",
                "value": 80
              }
            ]
          },
          "unit": "short"
        },
        "overrides": [
          {
            "matcher": {
              "id": "byName",
              "options": "kpi_type_code"
            },
            "properties": [
              {
                "id": "mappings",
                "value": [
                  {
                    "options": {
                      "RA_CAM_QUALITY": {
                        "index": 0,
                        "text": "CAM compliance"
                      },
                      "RA_CLOCK_DIFF": {
                        "index": 1,
                        "text": "Clock drift"
                      },
                      "RA_CONNECTED_PERCENTAGE": {
                        "index": 2,
                        "text": "Percentage of time connected (uptime)"
                      },
                      "RA_EXCEPTIONAL_CONDITION_PERCENTAGE": {
                        "index": 3,
                        "text": "Percentage red with special conditions"
                      },
                      "RA_MAP_FREQUENCY": {
                        "index": 4,
                        "text": "MAP frequency"
                      },
                      "RA_MAP_QUALITY": {
                        "index": 5,
                        "text": "MAP compliance"
                      },
                      "RA_PREDICTION_CONFIDENCE_PERCENTAGE": {
                        "index": 6,
                        "text": "Percentage prediction with high certainty (confidence)"
                      },
                      "RA_PREDICTION_LIKELY_DELTA": {
                        "index": 7,
                        "text": "Deviation prediction (likely)"
                      },
                      "RA_PREDICTION_LIKELY_PERCENTAGE": {
                        "index": 8,
                        "text": "Percent Prediction (Likely)"
                      },
                      "RA_PREDICTION_WINDOW_PERCENTAGE": {
                        "index": 26,
                        "text": "Percent Prediction (min/max)"
                      },
                      "RA_PREDICTION_WINDOW_SIZE": {
                        "index": 27,
                        "text": "Bandwidth prediction (min/max)"
                      },
                      "RA_PRIORITY_ANSWERED_PERCENTAGE": {
                        "index": 25,
                        "text": "Percentage of priority request answered"
                      },
                      "RA_PRIORITY_GRANTED_ETA_DELTA_EMERGENCY": {
                        "index": 18,
                        "text": "Deviation ETA granted priority request emergency services"
                      },
                      "RA_PRIORITY_GRANTED_ETA_DELTA_OTHER": {
                        "index": 19,
                        "text": "Deviation ETA assigned priority request other"
                      },
                      "RA_PRIORITY_GRANTED_ETA_GREEN_DELTA_EMERGENCY": {
                        "index": 20,
                        "text": "Time between ETA priority request and actually green emergency services"
                      },
                      "RA_PRIORITY_GRANTED_ETA_GREEN_DELTA_OTHER": {
                        "index": 21,
                        "text": "Tijd tussen ETA prioriteitsverzoek en daadwerkelijk groen overig"
                      },
                      "RA_PRIORITY_GRANTED_PERCENTAGE_EMERGENCY": {
                        "index": 22,
                        "text": "Percentage of emergency services priority request granted"
                      },
                      "RA_PRIORITY_GRANTED_PERCENTAGE_OTHER": {
                        "index": 23,
                        "text": "Percentage toegekend prioriteitsverzoek overig"
                      },
                      "RA_ROUNDTRIP_LATENCY": {
                        "index": 24,
                        "text": "Latency connection (round trip)"
                      },
                      "RA_SAT_MISSING_DAYS": {
                        "index": 9,
                        "text": "Days in production without iSAT"
                      },
                      "RA_SESSION_CREATIONS": {
                        "index": 10,
                        "text": "Connection attempts"
                      },
                      "RA_SPAT_FREQUENCY": {
                        "index": 11,
                        "text": "SPAT frequency"
                      },
                      "RA_SPAT_QUALITY": {
                        "index": 12,
                        "text": "SPAT compliance"
                      },
                      "RA_SRM_QUALITY": {
                        "index": 14,
                        "text": "SRM compliance"
                      },
                      "RA_SSM_QUALITY": {
                        "index": 13,
                        "text": "SSM compliance"
                      },
                      "RA_STATION_COUNT": {
                        "index": 15,
                        "text": "Traffic intensity"
                      },
                      "RA_SUBJECT_STATE": {
                        "index": 16,
                        "text": "Object status"
                      },
                      "RA_TLCCONF_QUALITY": {
                        "index": 17,
                        "text": "TLC Conf conformance"
                      }
                    },
                    "type": "value"
                  }
                ]
              }
            ]
          }
        ]
      },
      "gridPos": {
        "h": 16,
        "w": 24,
        "x": 0,
        "y": 0
      },
      "id": 12,
      "options": {
        "barRadius": 0,
        "barWidth": 0.49,
        "colorByField": "total_alerts",
        "fullHighlight": true,
        "groupWidth": 0.7,
        "legend": {
          "calcs": [],
          "displayMode": "table",
          "placement": "right",
          "showLegend": true
        },
        "orientation": "horizontal",
        "showValue": "always",
        "stacking": "normal",
        "tooltip": {
          "mode": "single",
          "sort": "none"
        },
        "xField": "kpi_type_code",
        "xTickLabelRotation": 0,
        "xTickLabelSpacing": 0
      },
      "targets": [
        {
          "datasource": {
            "type": "postgres",
            "uid": "${DS_TIMESCALE}"
          },
          "editorMode": "code",
          "format": "table",
          "rawQuery": true,
          "rawSql": "SELECT kpi_type_code, SUM(kpi_alert_count) as total_alerts\nFROM kpi_1d\nWHERE device_identifier IN (${device_identifier})\nAND time >= to_date('${start_date}', 'YYYY-MM')\nAND time < to_date('${end_date}', 'YYYY-MM') + INTERVAL '1 month'\nGROUP BY kpi_type_code;\n",
          "refId": "A",
          "sql": {
            "columns": [
              {
                "parameters": [],
                "type": "function"
              }
            ],
            "groupBy": [
              {
                "property": {
                  "type": "string"
                },
                "type": "groupBy"
              }
            ],
            "limit": 50
          }
        }
      ],
      "title": "The number of KPI samples that met the alert condition for each KPI type for Device ID${device_identifier}",
      "type": "barchart"
    },
    {
      "datasource": {
        "type": "postgres",
        "uid": "${DS_TIMESCALE}"
      },
      "description": "Display the average KPI value over time for a specific device.\n\n",
      "fieldConfig": {
        "defaults": {
          "color": {
            "mode": "palette-classic"
          },
          "custom": {
            "axisCenteredZero": false,
            "axisColorMode": "text",
            "axisLabel": "",
            "axisPlacement": "auto",
            "barAlignment": 0,
            "drawStyle": "line",
            "fillOpacity": 0,
            "gradientMode": "none",
            "hideFrom": {
              "legend": false,
              "tooltip": false,
              "viz": false
            },
            "lineInterpolation": "linear",
            "lineWidth": 1,
            "pointSize": 5,
            "scaleDistribution": {
              "type": "linear"
            },
            "showPoints": "auto",
            "spanNulls": false,
            "stacking": {
              "group": "A",
              "mode": "none"
            },
            "thresholdsStyle": {
              "mode": "off"
            }
          },
          "displayName": "Average KPI value",
          "mappings": [],
          "thresholds": {
            "mode": "absolute",
            "steps": [
              {
                "color": "green",
                "value": null
              },
              {
                "color": "red",
                "value": 80
              }
            ]
          }
        },
        "overrides": []
      },
      "gridPos": {
        "h": 8,
        "w": 12,
        "x": 0,
        "y": 16
      },
      "id": 10,
      "options": {
        "legend": {
          "calcs": [
            "min",
            "max",
            "count",
            "sum",
            "mean"
          ],
          "displayMode": "table",
          "placement": "bottom",
          "showLegend": true
        },
        "tooltip": {
          "mode": "single",
          "sort": "none"
        }
      },
      "targets": [
        {
          "datasource": {
            "type": "postgres",
            "uid": "${DS_TIMESCALE}"
          },
          "editorMode": "code",
          "format": "table",
          "rawQuery": true,
          "rawSql": "SELECT time, kpi_type_code, kpi_value_avg\nFROM kpi_1d\nWHERE device_identifier IN (${device_identifier})\nAND time >= to_date('${start_date}', 'YYYY-MM')\nAND time < to_date('${end_date}', 'YYYY-MM') + INTERVAL '1 month';",
          "refId": "A",
          "sql": {
            "columns": [
              {
                "parameters": [],
                "type": "function"
              }
            ],
            "groupBy": [
              {
                "property": {
                  "type": "string"
                },
                "type": "groupBy"
              }
            ],
            "limit": 50
          }
        }
      ],
      "title": "Average KPI value over time for Device ID ${device_identifier}",
      "type": "timeseries"
    },
    {
      "datasource": {
        "type": "postgres",
        "uid": "${DS_TIMESCALE}"
      },
      "fieldConfig": {
        "defaults": {
          "color": {
            "mode": "thresholds"
          },
          "custom": {
            "align": "auto",
            "cellOptions": {
              "type": "auto"
            },
            "inspect": false
          },
          "mappings": [],
          "thresholds": {
            "mode": "absolute",
            "steps": [
              {
                "color": "green",
                "value": null
              },
              {
                "color": "red",
                "value": 80
              }
            ]
          }
        },
        "overrides": []
      },
      "gridPos": {
        "h": 9,
        "w": 12,
        "x": 12,
        "y": 16
      },
      "id": 2,
      "options": {
        "cellHeight": "sm",
        "footer": {
          "countRows": false,
          "fields": "",
          "reducer": [
            "sum"
          ],
          "show": false
        },
        "showHeader": true
      },
      "pluginVersion": "9.5.2",
      "targets": [
        {
          "datasource": {
            "type": "postgres",
            "uid": "${DS_TIMESCALE}"
          },
          "editorMode": "code",
          "format": "table",
          "rawQuery": true,
          "rawSql": "SELECT * FROM kpi_type ORDER BY code",
          "refId": "A",
          "sql": {
            "columns": [
              {
                "parameters": [],
                "type": "function"
              }
            ],
            "groupBy": [
              {
                "property": {
                  "type": "string"
                },
                "type": "groupBy"
              }
            ],
            "limit": 50
          },
          "table": "kpi_1d"
        }
      ],
      "title": "kpi_type",
      "type": "table"
    },
    {
      "datasource": {
        "type": "postgres",
        "uid": "${DS_TIMESCALE}"
      },
      "fieldConfig": {
        "defaults": {
          "custom": {
            "hideFrom": {
              "legend": false,
              "tooltip": false,
              "viz": false
            },
            "scaleDistribution": {
              "type": "linear"
            }
          }
        },
        "overrides": []
      },
      "gridPos": {
        "h": 8,
        "w": 12,
        "x": 0,
        "y": 24
      },
      "id": 11,
      "options": {
        "calculate": false,
        "calculation": {
          "xBuckets": {
            "mode": "count"
          },
          "yBuckets": {
            "mode": "count"
          }
        },
        "cellGap": 1,
        "color": {
          "exponent": 0.5,
          "fill": "dark-orange",
          "mode": "scheme",
          "reverse": false,
          "scale": "exponential",
          "scheme": "Blues",
          "steps": 64
        },
        "exemplars": {
          "color": "rgba(255,0,255,0.7)"
        },
        "filterValues": {
          "le": 1e-9
        },
        "legend": {
          "show": true
        },
        "rowsFrame": {
          "layout": "auto"
        },
        "tooltip": {
          "show": true,
          "yHistogram": false
        },
        "yAxis": {
          "axisPlacement": "left",
          "reverse": false
        }
      },
      "pluginVersion": "9.5.2",
      "targets": [
        {
          "datasource": {
            "type": "postgres",
            "uid": "${DS_TIMESCALE}"
          },
          "editorMode": "code",
          "format": "table",
          "rawQuery": true,
          "rawSql": "SELECT time, kpi_type_code, kpi_value_avg\nFROM kpi_1d\nWHERE device_identifier = ${device_identifier}\nAND time >= to_date('${start_date}', 'YYYY-MM')\nAND time < to_date('${end_date}', 'YYYY-MM') + INTERVAL '1 month'\n",
          "refId": "A",
          "sql": {
            "columns": [
              {
                "parameters": [],
                "type": "function"
              }
            ],
            "groupBy": [
              {
                "property": {
                  "type": "string"
                },
                "type": "groupBy"
              }
            ],
            "limit": 50
          }
        }
      ],
      "title": "The density or intensity of KPI values over time.",
      "type": "heatmap"
    },
    {
      "datasource": {
        "type": "postgres",
        "uid": "${DS_TIMESCALE}"
      },
      "description": "",
      "fieldConfig": {
        "defaults": {
          "mappings": [],
          "thresholds": {
            "mode": "percentage",
            "steps": [
              {
                "color": "green",
                "value": null
              },
              {
                "color": "orange",
                "value": 70
              },
              {
                "color": "red",
                "value": 85
              }
            ]
          }
        },
        "overrides": []
      },
      "gridPos": {
        "h": 8,
        "w": 12,
        "x": 12,
        "y": 25
      },
      "id": 9,
      "options": {
        "orientation": "auto",
        "reduceOptions": {
          "calcs": [
            "lastNotNull"
          ],
          "fields": "",
          "values": false
        },
        "showThresholdLabels": false,
        "showThresholdMarkers": true
      },
      "pluginVersion": "9.5.2",
      "targets": [
        {
          "datasource": {
            "type": "postgres",
            "uid": "${DS_TIMESCALE}"
          },
          "editorMode": "code",
          "format": "table",
          "rawQuery": true,
          "rawSql": "SELECT SUM(kpi_alert_count) as total_alerts\nFROM kpi_1d\nWHERE device_identifier IN (${device_identifier})\nAND time >= to_date('${start_date}', 'YYYY-MM')\nAND time < to_date('${end_date}', 'YYYY-MM') + INTERVAL '1 month';",
          "refId": "A",
          "sql": {
            "columns": [
              {
                "parameters": [],
                "type": "function"
              }
            ],
            "groupBy": [
              {
                "property": {
                  "type": "string"
                },
                "type": "groupBy"
              }
            ],
            "limit": 50
          }
        }
      ],
      "title": "KPI Alert Count for Device ID${device_identifier}",
      "transformations": [],
      "transparent": true,
      "type": "gauge"
    },
    {
      "datasource": {
        "type": "postgres",
        "uid": "${DS_TIMESCALE}"
      },
      "description": "",
      "fieldConfig": {
        "defaults": {
          "color": {
            "mode": "palette-classic"
          },
          "custom": {
            "hideFrom": {
              "legend": false,
              "tooltip": false,
              "viz": false
            }
          },
          "mappings": [],
          "unit": "short"
        },
        "overrides": []
      },
      "gridPos": {
        "h": 8,
        "w": 12,
        "x": 0,
        "y": 32
      },
      "id": 8,
      "options": {
        "displayLabels": [
          "percent"
        ],
        "legend": {
          "displayMode": "list",
          "placement": "right",
          "showLegend": true,
          "values": []
        },
        "pieType": "pie",
        "reduceOptions": {
          "calcs": [
            "lastNotNull"
          ],
          "fields": "",
          "values": true
        },
        "tooltip": {
          "mode": "single",
          "sort": "none"
        }
      },
      "pluginVersion": "9.5.2",
      "targets": [
        {
          "datasource": {
            "type": "postgres",
            "uid": "${DS_TIMESCALE}"
          },
          "editorMode": "code",
          "format": "table",
          "rawQuery": true,
          "rawSql": "SELECT kpi_alert_condition_type_last, COUNT(*) as count\nFROM kpi_1d\nWHERE device_identifier IN (${device_identifier})\nAND time >= to_date('${start_date}', 'YYYY-MM')\nAND time < to_date('${end_date}', 'YYYY-MM') + INTERVAL '1 month'\nGROUP BY kpi_alert_condition_type_last;\n",
          "refId": "A",
          "sql": {
            "columns": [
              {
                "parameters": [],
                "type": "function"
              }
            ],
            "groupBy": [
              {
                "property": {
                  "type": "string"
                },
                "type": "groupBy"
              }
            ],
            "limit": 50
          }
        }
      ],
      "title": "The distribution of different alert conditions.",
      "type": "piechart"
    },
    {
      "datasource": {
        "type": "postgres",
        "uid": "${DS_TIMESCALE}"
      },
      "fieldConfig": {
        "defaults": {
          "color": {
            "mode": "palette-classic"
          },
          "custom": {
            "axisCenteredZero": false,
            "axisColorMode": "text",
            "axisLabel": "",
            "axisPlacement": "auto",
            "barAlignment": 0,
            "drawStyle": "line",
            "fillOpacity": 0,
            "gradientMode": "none",
            "hideFrom": {
              "legend": false,
              "tooltip": false,
              "viz": false
            },
            "lineInterpolation": "linear",
            "lineWidth": 1,
            "pointSize": 5,
            "scaleDistribution": {
              "type": "linear"
            },
            "showPoints": "auto",
            "spanNulls": false,
            "stacking": {
              "group": "A",
              "mode": "none"
            },
            "thresholdsStyle": {
              "mode": "off"
            }
          },
          "mappings": [],
          "thresholds": {
            "mode": "absolute",
            "steps": [
              {
                "color": "green",
                "value": null
              },
              {
                "color": "red",
                "value": 80
              }
            ]
          }
        },
        "overrides": []
      },
      "gridPos": {
        "h": 8,
        "w": 12,
        "x": 0,
        "y": 40
      },
      "id": 5,
      "options": {
        "legend": {
          "calcs": [],
          "displayMode": "list",
          "placement": "bottom",
          "showLegend": true
        },
        "tooltip": {
          "mode": "single",
          "sort": "none"
        }
      },
      "pluginVersion": "9.5.2",
      "targets": [
        {
          "datasource": {
            "type": "postgres",
            "uid": "${DS_TIMESCALE}"
          },
          "editorMode": "code",
          "format": "table",
          "rawQuery": true,
          "rawSql": "SELECT time, kpi_type_code, kpi_value_avg, kpi_alert_count, kpi_alert_condition_text_last\nFROM kpi_1d\nWHERE time BETWEEN '2023-01-01' AND '2023-01-31';\n\n",
          "refId": "A",
          "sql": {
            "columns": [
              {
                "parameters": [],
                "type": "function"
              }
            ],
            "groupBy": [
              {
                "property": {
                  "type": "string"
                },
                "type": "groupBy"
              }
            ],
            "limit": 50
          }
        }
      ],
      "title": "Panel Title",
      "type": "timeseries"
    },
    {
      "datasource": {
        "type": "postgres",
        "uid": "${DS_TIMESCALE}"
      },
      "fieldConfig": {
        "defaults": {
          "color": {
            "mode": "thresholds"
          },
          "custom": {
            "align": "auto",
            "cellOptions": {
              "type": "auto"
            },
            "inspect": false
          },
          "mappings": [],
          "thresholds": {
            "mode": "absolute",
            "steps": [
              {
                "color": "green",
                "value": null
              },
              {
                "color": "red",
                "value": 80
              }
            ]
          }
        },
        "overrides": []
      },
      "gridPos": {
        "h": 9,
        "w": 12,
        "x": 0,
        "y": 48
      },
      "id": 1,
      "options": {
        "cellHeight": "sm",
        "footer": {
          "countRows": false,
          "fields": "",
          "reducer": [
            "sum"
          ],
          "show": false
        },
        "showHeader": true
      },
      "pluginVersion": "9.5.2",
      "targets": [
        {
          "datasource": {
            "type": "postgres",
            "uid": "${DS_TIMESCALE}"
          },
          "editorMode": "code",
          "format": "table",
          "rawQuery": true,
          "rawSql": "SELECT * FROM kpi_1d WHERE time = (select max(time) from kpi_1d) AND device_identifier = (SELECT max(device_identifier) FROM kpi_1d) ORDER BY kpi_type_code ",
          "refId": "A",
          "sql": {
            "columns": [
              {
                "parameters": [],
                "type": "function"
              }
            ],
            "groupBy": [
              {
                "property": {
                  "type": "string"
                },
                "type": "groupBy"
              }
            ],
            "limit": 50
          },
          "table": "kpi_1d"
        }
      ],
      "title": "kpi_1d",
      "type": "table"
    },
    {
      "datasource": {
        "type": "postgres",
        "uid": "${DS_TIMESCALE}"
      },
      "gridPos": {
        "h": 11,
        "w": 24,
        "x": 0,
        "y": 57
      },
      "id": 3,
      "options": {
        "folderId": 0,
        "maxItems": 10,
        "query": "",
        "showHeadings": false,
        "showRecentlyViewed": false,
        "showSearch": true,
        "showStarred": false,
        "tags": []
      },
      "pluginVersion": "9.5.2",
      "title": "Dashboards",
      "type": "dashlist"
    }
  ],
  "refresh": "",
  "schemaVersion": 38,
  "style": "dark",
  "tags": [],
  "templating": {
    "list": [
      {
        "current": {},
        "datasource": {
          "type": "postgres",
          "uid": "${DS_TIMESCALE}"
        },
        "definition": "SELECT DISTINCT device_identifier FROM kpi_1d ORDER BY device_identifier;\n",
        "hide": 0,
        "includeAll": true,
        "label": "Device Identifier",
        "multi": false,
        "name": "device_identifier",
        "options": [],
        "query": "SELECT DISTINCT device_identifier FROM kpi_1d ORDER BY device_identifier;\n",
        "refresh": 1,
        "regex": "",
        "skipUrlSync": false,
        "sort": 0,
        "type": "query"
      },
      {
        "current": {},
        "datasource": {
          "type": "postgres",
          "uid": "${DS_TIMESCALE}"
        },
        "definition": "SELECT DISTINCT to_char(time, 'YYYY-MM') as month_year\nFROM kpi_1d\nORDER BY month_year;\n",
        "hide": 0,
        "includeAll": false,
        "label": "Start Date",
        "multi": false,
        "name": "start_date",
        "options": [],
        "query": "SELECT DISTINCT to_char(time, 'YYYY-MM') as month_year\nFROM kpi_1d\nORDER BY month_year;\n",
        "refresh": 2,
        "regex": "",
        "skipUrlSync": false,
        "sort": 0,
        "type": "query"
      },
      {
        "current": {},
        "datasource": {
          "type": "postgres",
          "uid": "${DS_TIMESCALE}"
        },
        "definition": "SELECT DISTINCT to_char(time, 'YYYY-MM') as month_year\nFROM kpi_1d\nORDER BY month_year;\n",
        "hide": 0,
        "includeAll": false,
        "label": "End Date",
        "multi": false,
        "name": "end_date",
        "options": [],
        "query": "SELECT DISTINCT to_char(time, 'YYYY-MM') as month_year\nFROM kpi_1d\nORDER BY month_year;\n",
        "refresh": 1,
        "regex": "",
        "skipUrlSync": false,
        "sort": 0,
        "type": "query"
      },
      {
        "current": {},
        "datasource": {
          "type": "postgres",
          "uid": "${DS_TIMESCALE}"
        },
        "definition": "SELECT DISTINCT org_identifier FROM kpi_1d ORDER BY org_identifier;\n",
        "hide": 0,
        "includeAll": true,
        "label": "Organizational Identifier",
        "multi": true,
        "name": "org_identifier",
        "options": [],
        "query": "SELECT DISTINCT org_identifier FROM kpi_1d ORDER BY org_identifier;\n",
        "refresh": 1,
        "regex": "",
        "skipUrlSync": false,
        "sort": 0,
        "type": "query"
      }
    ]
  },
  "time": {
    "from": "2022-11-17T00:00:00.000Z",
    "to": "2023-01-25T00:00:00.000Z"
  },
  "timepicker": {
    "hidden": true
  },
  "timezone": "Europe/Amsterdam",
  "title": "Testing",
  "uid": "e567dc61-e358-4c0e-ae4c-8ee124f17927",
  "version": 42,
  "weekStart": "monday"
}